mcp_server_docs/__init__.py
mcp_server_docs/explorer.py
mcp_server_docs/server.py
mcp_server_docs-0.1.6.dist-info/METADATA
mcp_server_docs-0.1.6.dist-info/WHEEL
mcp_server_docs-0.1.6.dist-info/entry_points.txt
mcp_server_docs-0.1.6.dist-info/RECORD
