Metadata-Version: 2.4
Name: mcp-server-docs
Version: 0.1.6
Summary: An MCP Server that makes it easy to load documentation files from locally available repositories
Requires-Python: >=3.11
Requires-Dist: aiofiles>=24.1.0
Requires-Dist: mcp>=1.2.0
Requires-Dist: pyyaml
